Workbook

Sheet Inputs
A1: Orviko Conservative Pricing Model
A3: Commercial Inputs | B3: Value | C3: Notes | E3: Policy Inputs | F3: Value | G3: Notes
A4: VAT included in public price | B4: 0.11 | C4: PPN 11% sudah termasuk harga paket | E4: Operational safety reserve | F4: 0.14 | G4: Cadangan tambahan sebelum menentukan sesi jual
A5: Bank fee | B5: 0.14 | C5: Fee Mastercard BCA
A6: Target gross margin | B6: 0.3 | C6: Margin target setelah VAT dikeluarkan | E6: Use conservative session mode | F6: No-cache 45-minute replay | G6: Baseline pricing yang dipakai untuk paket
A7: AI cost share | B7: =1/(1+B6) -> 0.76923077 | C7: Formula = 1 - target gross margin | E7: CV/JD policy | F7: Fair usage | G7: Tidak memakai hard cap kaku
A8: USD to IDR | B8: 20000 | C8: Asumsi kurs tetap | E8: Reference sample duration (minutes) | F8: 8.4 | G8: Durasi audio nyata yang dipakai replay
A9: Mini public price | B9: 29000 | C9: Harga customer final | E9: Reference sample help clicks | F9: 7 | G9: Jumlah klik Bantu Jawab dari sampel nyata
A10: Starter public price | B10: 98000 | C10: Harga customer final | E10: Primary help action | F10: Bantu Jawab | G10: Aksi terberat yang dipakai sebagai baseline
A11: Pro public price | B11: 379000 | C11: Harga customer final | E11: Notes | F11: Production-like replay | G11: Sudah mencakup session prompt + CV + JD + domain
A12: Interview duration (minutes) | B12: 45 | C12: Unit sesi utama untuk pricing
A14: Core formula drivers below are referenced by every other sheet.

Sheet Benchmarks
A1: Measured Runtime Benchmarks
A3: Metric | B3: Value | C3: Notes | E3: Pricing Metric | F3: Value | G3: Notes
A4: Transcribe sample audio input tokens | B4: 5047 | C4: Measured from demo-orviko-awal.MP3 | E4: Transcribe audio price per 1M tokens (USD) | F4: 3 | G4: Official pricing
A5: Transcribe sample output tokens | B5: 1284 | C5: Measured from demo-orviko-awal.MP3 | E5: Transcribe output price per 1M tokens (USD) | F5: 5 | G5: Official pricing
A6: Realtime replay input tokens | B6: 39017 | C6: Corrected production-like replay total | E6: Realtime input price per 1M tokens (USD) | F6: 0.6 | G6: Official pricing
A7: Realtime replay cached input tokens | B7: 27392 | C7: Measured cached input in replay | E7: Realtime cached input price per 1M tokens (USD) | F7: 0.06 | G7: Official pricing
A8: Realtime replay output tokens | B8: 777 | C8: Corrected production-like replay total | E8: Realtime output price per 1M tokens (USD) | F8: 2.4 | G8: Official pricing
A9: Sample duration (minutes) | B9: =Inputs!F8 -> 8.4 | C9: Linked from Inputs | E9: gpt-5-mini input price per 1M tokens (USD) | F9: 0.25 | G9: Official pricing
A10: 45-minute scale factor | B10: =Inputs!B12/B9 -> 5.3571429 | C10: Target duration / sample duration | E10: gpt-5-mini output price per 1M tokens (USD) | F10: 2 | G10: Official pricing
A11: Observed click rate per minute | B11: =Inputs!F9/B9 -> 0.83333333 | C11: Sample clicks / sample duration | E11: Transcribe sample cost (USD) | F11: =(B4/1000000)*F4 + (B5/1000000)*F5 -> 0.021561 | G11: Measured sample priced from token counts
A12: Observed clicks per 45-minute session | B12: =B11*Inputs!B12 -> 37.5 | C12: Click rate scaled to target duration | E12: Realtime sample cost with cache (USD) | F12: =((B6-B7)/1000000)*F6 + (B7/1000000)*F7 + (B8/1000000)*F8 -> 0.01048332 | G12: Uses cached-input discount
A13: CV benchmark input tokens | B13: 2405 | C13: Average measured gpt-5-mini CV preprocess input | E13: Realtime sample cost no-cache (USD) | F13: =(B6/1000000)*F6 + (B8/1000000)*F8 -> 0.025275 | G13: Conservative pricing baseline
A14: CV benchmark output tokens | B14: 4747 | C14: Average measured gpt-5-mini CV preprocess output | E14: Total sample cost with cache (USD) | F14: =F11+F12 -> 0.03204432 | G14: Transcribe + realtime with cache
A15: JD benchmark input tokens | B15: 1598 | C15: Average measured gpt-5-mini JD preprocess input | E15: Total sample cost no-cache (USD) | F15: =F11+F13 -> 0.046836 | G15: Transcribe + realtime no-cache
A16: JD benchmark output tokens | B16: 2915.4 | C16: Average measured gpt-5-mini JD preprocess output
A18: Derived 45-minute costs | B18: Formula result | C18: Notes | E18: Onboarding costs | F18: Formula result | G18: Notes
A19: 45-minute total cost with cache (USD) | B19: =F14*B10 -> 0.171666 | C19: Sample total cost x scale factor | E19: CV preprocess cost (USD) | F19: =(B13/1000000)*F9 + (B14/1000000)*F10 -> 0.01009525 | G19: Measured benchmark priced with gpt-5-mini
A20: 45-minute total cost no-cache (USD) | B20: =F15*B10 -> 0.25090714 | C20: Conservative session baseline | E20: JD preprocess cost (USD) | F20: =(B15/1000000)*F9 + (B16/1000000)*F10 -> 0.0062303 | G20: Measured benchmark priced with gpt-5-mini
A21: 45-minute total cost with cache (IDR) | B21: =B19*Inputs!B8 -> 3433.32 | C21: USD x FX | E21: CV preprocess cost (IDR) | F21: =F19*Inputs!B8 -> 201.905 | G21: USD x FX
A22: 45-minute total cost no-cache (IDR) | B22: =B20*Inputs!B8 -> 5018.1429 | C22: USD x FX | E22: JD preprocess cost (IDR) | F22: =F20*Inputs!B8 -> 124.606 | G22: USD x FX
A23: Rounded conservative session cost (IDR) | B23: =ROUND(B22,0) -> 5018 | C23: Rounded for packaging

Sheet Packages
A1: Package Capacity Model
A3: Package | B3: Public Price | C3: Price ex VAT | D3: AI Budget | E3: Conservative Session Cost | F3: Theoretical Max Sessions | G3: Recommended Sessions | H3: Live Cost Used | I3: Remaining Onboarding Buffer | J3: Remaining Buffer Status
A4: Mini | B4: =Inputs!B9 -> 29000 | C4: =(B4-Inputs!$B$5)/(1+Inputs!$B$4) -> 26126 | D4: =C4*Inputs!B7 -> 20096.923 | E4: =Benchmarks!B23 -> 5018 | F4: =D4/E4 -> 4.0049667 | G4: =ROUNDDOWN((D4*(1-Inputs!F4))/E4,0) -> 3 | H4: =G4*E4 -> 15054 | I4: =D4-H4 -> 5042.9231 | J4: =IF(I4>=Benchmarks!F21+Benchmarks!F22,"Healthy","Tight") -> Healthy
A5: Starter | B5: =Inputs!B10 -> 98000 | C5: =(B5-Inputs!$B$5)/(1+Inputs!$B$4) -> 88288.162 | D5: =C5*Inputs!B7 -> 67913.971 | E5: =Benchmarks!B23 -> 5018 | F5: =D5/E5 -> 13.534072 | G5: 12 | H5: =G5*E5 -> 60216 | I5: =D5-H5 -> 7697.9709 | J5: =IF(I5>=Benchmarks!F21+Benchmarks!F22,"Healthy","Tight") -> Healthy
A6: Pro | B6: =Inputs!B11 -> 379000 | C6: =(B6-Inputs!$B$5)/(1+Inputs!$B$4) -> 341441.32 | D6: =C6*Inputs!B7 -> 262647.17 | E6: =Benchmarks!B23 -> 5018 | F6: =D6/E6 -> 52.341006 | G6: 50 | H6: =G6*E6 -> 250900 | I6: =D6-H6 -> 11747.166 | J6: =IF(I6>=Benchmarks!F21+Benchmarks!F22,"Healthy","Tight") -> Healthy
A8: Onboarding capacity from remaining buffer | B8: Mini | C8: Starter | D8: Pro | E8: Formula | F8: Notes
A9: CV only capacity | B9: =I4/Benchmarks!F21 -> 24.976712 | C9: =I5/Benchmarks!F21 -> 38.126698 | D9: =I6/Benchmarks!F21 -> 58.181648 | E9: =Benchmarks!F21 -> 201.905 | F9: Theoretical fair-usage room
A10: JD only capacity | B10: =I4/Benchmarks!F22 -> 40.470949 | C10: =I5/Benchmarks!F22 -> 61.778493 | D10: =I6/Benchmarks!F22 -> 94.274478 | E10: =Benchmarks!F22 -> 124.606 | F10: Theoretical fair-usage room
A11: CV+JD pair capacity | B11: =I4/(Benchmarks!F21+Benchmarks!F22) -> 15.44488 | C11: =I5/(Benchmarks!F21+Benchmarks!F22) -> 23.576452 | D11: =I6/(Benchmarks!F21+Benchmarks!F22) -> 35.977856 | E11: =Benchmarks!F21+Benchmarks!F22 -> 326.511 | F11: Useful simple planning unit
A12: Implied target reserve % kept | B12: =I4/D4 -> 0.25093011 | C12: =I5/D5 -> 0.11334886 | D12: =I6/D6 -> 0.044726032 | E12: 1 | F12: Checks policy reserve actually preserved

Sheet ROI
B2: Paket | C2: Harga | D2: Margin 30% | E2: Margin
B4: Mini | C4: =Packages!D4*1.11 -> 22307.585 | D4: =C4*1.3 -> 28999.86 | E4: =D4-C4 -> 6692.2754
B5: Starter | C5: =Packages!D5*1.11 -> 75384.508 | D5: =C5*1.3 -> 97999.86 | E5: =D5-C5 -> 22615.352
B6: Pro | C6: =Packages!D6*1.11 -> 291538.35 | D6: =C6*1.3 -> 378999.86 | E6: =D6-C6 -> 87461.506
B8: Paket | C8: Jumlah Users
C9: 10 | D9: 20 | E9: 50 | F9: 75 | G9: 100 | H9: 300 | I9: 500 | J9: 1000 | K9: 3500 | L9: =J19 -> 70000
B10: Mini | C10: =E4*C$9 -> 66922.754 | D10: =E4*D$9 -> 133845.51 | E10: =E4*E$9 -> 334613.77 | F10: =E4*F$9 -> 501920.65 | G10: =E4*G$9 -> 669227.54 | H10: =E4*H$9 -> 2007682.6 | I10: =E4*I$9 -> 3346137.7 | J10: =E4*J$9 -> 6692275.4 | K10: =E4*K$9 -> 23422964 | L10: =E4*L$9 -> 4.6845928e+08
B11: Starter | C11: =E5*C$9 -> 226153.52 | D11: =E5*D$9 -> 452307.05 | E11: =E5*E$9 -> 1130767.6 | F11: =E5*F$9 -> 1696151.4 | G11: =E5*G$9 -> 2261535.2 | H11: =E5*H$9 -> 6784605.7 | I11: =E5*I$9 -> 11307676 | J11: =E5*J$9 -> 22615352 | K11: =E5*K$9 -> 79153733 | L11: =E5*L$9 -> 1.5830747e+09
B12: Pro | C12: =E6*C$9 -> 874615.06 | D12: =E6*D$9 -> 1749230.1 | E12: =E6*E$9 -> 4373075.3 | F12: =E6*F$9 -> 6559613 | G12: =E6*G$9 -> 8746150.6 | H12: =E6*H$9 -> 26238452 | I12: =E6*I$9 -> 43730753 | J12: =E6*J$9 -> 87461506 | K12: =E6*K$9 -> 3.0611527e+08 | L12: =E6*L$9 -> 6.1223054e+09
J18: 7000000
J19: =J18*0.01 -> 70000
